dimipy/__init__.py
dimipy/core.py
dimipy/formatters.py
dimipy/constants/__init__.py
dimipy/constants/defined.py
dimipy/constants/math.py
dimipy/dimensions/__init__.py
dimipy/dimensions/electric.py
dimipy/dimensions/luminous.py
dimipy/dimensions/magnetic.py
dimipy/prefixes/__init__.py
dimipy/prefixes/binary.py
dimipy/prefixes/metric.py
dimipy/units/__init__.py
dimipy/units/angle.py
dimipy/units/astronomical.py
dimipy/units/imperial.py
dimipy/units/information.py
dimipy/units/planck.py
dimipy/units/si.py
dimipy/units/us.py
dimipy-0.0.1.dist-info/LICENSE
dimipy-0.0.1.dist-info/METADATA
dimipy-0.0.1.dist-info/WHEEL
dimipy-0.0.1.dist-info/top_level.txt
dimipy-0.0.1.dist-info/RECORD
