Metadata-Version: 2.2
Name: dimipy
Version: 0.0.1
Summary: library for dimensional analysis and unit conversion
Author-email: Jean-Raphaël Gaglione <jr.gaglione@yahoo.fr>
License: MIT License
Project-URL: Homepage, https://github.com/cryhot/dimipy
Project-URL: Repository, https://github.com/cryhot/dimipy.git
Project-URL: Issues, https://github.com/cryhot/dimipy/issues
Keywords: units-of-measure,dimensional-analysis
Classifier: Programming Language :: Python :: 3
Classifier: Operating System :: OS Independent
Classifier: License :: OSI Approved :: MIT License
Classifier: Topic :: Scientific/Engineering
Classifier: Topic :: Utilities
Classifier: Intended Audience :: Science/Research
Classifier: Intended Audience :: Manufacturing
Requires-Python: >=3.6
License-File: LICENSE
Requires-Dist: termcolor
Provides-Extra: dev
Requires-Dist: termcolor; extra == "dev"
Requires-Dist: ipython; extra == "dev"
